image_caption_editor/__init__.py
image_caption_editor/app.py
image_caption_editor/run.py
image_caption_editor-0.1.2.dist-info/LICENSE
image_caption_editor-0.1.2.dist-info/METADATA
image_caption_editor-0.1.2.dist-info/WHEEL
image_caption_editor-0.1.2.dist-info/entry_points.txt
image_caption_editor-0.1.2.dist-info/top_level.txt
image_caption_editor-0.1.2.dist-info/RECORD
